FineCache/CachedCall.py
FineCache/FineCache.py
FineCache/__init__.py
FineCache/utils.py
FineCache-0.2.1.dist-info/LICENSE
FineCache-0.2.1.dist-info/METADATA
FineCache-0.2.1.dist-info/WHEEL
FineCache-0.2.1.dist-info/top_level.txt
FineCache-0.2.1.dist-info/RECORD
