Metadata-Version: 2.1
Name: FineCache
Version: 0.2.1
Summary: 科研项目中实验记录工具
Home-page: https://github.com/ciaranchen/FineCache
Author: Ciaran Chen
Author-email: ciaranchen <ciaranchen@qq.com>
License: MIT
Requires-Python: >=3.9.6
License-File: LICENSE
